[
    {
        "type": "checkbox",
        "label": "Enabled",
        "placeholder": "",
        "name": "active",
        "objectKey": "",
        "isRequired": false,
        "optionData": [],
        "value": false
    },
    {
        "type": "checkbox",
        "label": "Default",
        "placeholder": "",
        "name": "defaultSelected",
        "objectKey": "",
        "isRequired": false,
        "optionData": [],
        "value": false
    },
    {
        "type": "dropdown",
        "label": "Environment",
        "placeholder": "Please select environment",
        "name": "enviroment",
        "objectKey": "",
        "isRequired": false,
        "optionData": [
            {
                "id": "test",
                "label": "Test"
            },
            {
                "id": "prod",
                "label": "Prod"
            }
        ],
        "value": ""
    },
    {
        "type": "summernote",
        "label": "Cheque to be made to this address",
        "placeholder": "Cheque to be made to this address",
        "name": "address",
        "objectKey": "integrationKeys",
        "isRequired": false,
        "optionData": [],
        "value": ""
    }
]